pyaml/__init__.py
pyaml/accelerator.py
pyaml/arrays/array.py
pyaml/arrays/bpm.py
pyaml/arrays/bpm_array.py
pyaml/arrays/cfm_magnet.py
pyaml/arrays/cfm_magnet_array.py
pyaml/arrays/element.py
pyaml/arrays/element_array.py
pyaml/arrays/magnet.py
pyaml/arrays/magnet_array.py
pyaml/arrays/serialized_magnet.py
pyaml/arrays/serialized_magnet_array.py
pyaml/bpm/bpm.py
pyaml/bpm/bpm_model.py
pyaml/bpm/bpm_simple_model.py
pyaml/bpm/bpm_tiltoffset_model.py
pyaml/common/__init__.py
pyaml/common/abstract.py
pyaml/common/abstract_aggregator.py
pyaml/common/constants.py
pyaml/common/element.py
pyaml/common/element_holder.py
pyaml/common/exception.py
pyaml/configuration/__init__.py
pyaml/configuration/csvcurve.py
pyaml/configuration/csvmatrix.py
pyaml/configuration/curve.py
pyaml/configuration/factory.py
pyaml/configuration/fileloader.py
pyaml/configuration/inline_curve.py
pyaml/configuration/inline_matrix.py
pyaml/configuration/matrix.py
pyaml/control/__init__.py
pyaml/control/abstract_impl.py
pyaml/control/controlsystem.py
pyaml/control/deviceaccess.py
pyaml/control/deviceaccesslist.py
pyaml/control/readback_value.py
pyaml/diagnostics/tune_monitor.py
pyaml/external/pySC_interface.py
pyaml/lattice/__init__.py
pyaml/lattice/abstract_impl.py
pyaml/lattice/attribute_linker.py
pyaml/lattice/element.py
pyaml/lattice/lattice_elements_linker.py
pyaml/lattice/polynom_info.py
pyaml/lattice/simulator.py
pyaml/magnet/__init__.py
pyaml/magnet/cfm_magnet.py
pyaml/magnet/corrector.py
pyaml/magnet/function_mapping.py
pyaml/magnet/hcorrector.py
pyaml/magnet/identity_cfm_model.py
pyaml/magnet/identity_model.py
pyaml/magnet/linear_cfm_model.py
pyaml/magnet/linear_model.py
pyaml/magnet/linear_serialized_model.py
pyaml/magnet/magnet.py
pyaml/magnet/model.py
pyaml/magnet/octupole.py
pyaml/magnet/quadrupole.py
pyaml/magnet/serialized_magnet.py
pyaml/magnet/sextupole.py
pyaml/magnet/skewoctu.py
pyaml/magnet/skewquad.py
pyaml/magnet/skewsext.py
pyaml/magnet/spline_model.py
pyaml/magnet/vcorrector.py
accelerator_middle_layer-0.2.1.dist-info/METADATA
accelerator_middle_layer-0.2.1.dist-info/WHEEL
accelerator_middle_layer-0.2.1.dist-info/licenses/LICENSE
accelerator_middle_layer-0.2.1.dist-info/RECORD
