Metadata-Version: 2.4
Name: accelerator-middle-layer
Version: 0.2.1
Summary: Python Accelerator Middle Layer
Project-URL: Homepage, https://github.com/python-accelerator-middle-layer/pyaml
Project-URL: Documentation, https://python-accelerator-middle-layer.github.io/pyaml/
Project-URL: Repository, https://github.com/python-accelerator-middle-layer/pyaml.git
Maintainer-email: Simone Maria Liuzzo <simone.liuzzo@esrf.fr>
License-File: LICENSE
Keywords: Accelerator,Commissioning,Digital Twin,Operation,Synchrotron,Tuning
Classifier: Development Status :: 3 - Alpha
Classifier: Intended Audience :: Science/Research
Classifier: Natural Language :: English
Classifier: Programming Language :: Python
Classifier: Programming Language :: Python :: 3 :: Only
Classifier: Programming Language :: Python :: 3.9
Classifier: Programming Language :: Python :: 3.10
Classifier: Programming Language :: Python :: 3.11
Classifier: Programming Language :: Python :: 3.12
Classifier: Topic :: Scientific/Engineering :: Physics
Requires-Python: >=3.11
Requires-Dist: accelerator-toolbox>=0.6.1
Requires-Dist: h5py
Requires-Dist: matplotlib
Requires-Dist: numpy>=1.21.0
Requires-Dist: pydantic>=2.11.7
Requires-Dist: pyyaml>=6.0.2
Requires-Dist: scipy>=1.7.3
Provides-Extra: dev
Requires-Dist: mypy; extra == 'dev'
Requires-Dist: pre-commit; extra == 'dev'
Requires-Dist: pytest; extra == 'dev'
Requires-Dist: ruff; extra == 'dev'
Provides-Extra: doc
Requires-Dist: myst-nb; extra == 'doc'
Requires-Dist: myst-parser; extra == 'doc'
Requires-Dist: pydata-sphinx-theme; extra == 'doc'
Requires-Dist: sphinx-copybutton; extra == 'doc'
Requires-Dist: sphinx-design; extra == 'doc'
Requires-Dist: sphinx~=8.1; extra == 'doc'
Provides-Extra: test
Requires-Dist: pytest-cov>=3.0; extra == 'test'
Requires-Dist: pytest>=7.4; extra == 'test'
